hardin/SGDTrainer.py
hardin/__init__.py
hardin/layers.py
hardin/loss.py
hardin/network.py
hardin/plots.py
hardin/tensor.py
hardin-0.1.dist-info/METADATA
hardin-0.1.dist-info/WHEEL
hardin-0.1.dist-info/top_level.txt
hardin-0.1.dist-info/RECORD
