Metadata-Version: 2.1
Name: hardin
Version: 0.1
Summary: A mini Deep Learning Framework
Home-page: https://gitlab2.informatik.uni-wuerzburg.de/s421904/hardin
Author: Tudor-Andrei Dumitrascu
Author-email: tudorandrei.dumitrascu@gmail.com
License: MIT
Platform: UNKNOWN
Requires-Dist: numpy
